my_test_project/__init__.py
my_test_project-0.1.1.dist-info/WHEEL
my_test_project-0.1.1.dist-info/METADATA
my_test_project-0.1.1.dist-info/RECORD
